Metadata-Version: 2.1
Name: tf-dataclass
Version: 0.1.2
Summary: Dataclasses for TensorFlow
Home-page: https://github.com/alexeytochin/tf-dataclass
Author: Alexey Tochin
Author-email: alexey.tochin@gmail.com
License: Apache 2.0
Keywords: tensorflow,dataclass
Platform: UNKNOWN
Classifier: Development Status :: 4 - Beta
Classifier: Intended Audience :: Science/Research
Classifier: Intended Audience :: Developers
Classifier: License :: OSI Approved :: Apache Software License
Classifier: Operating System :: POSIX :: Linux
Classifier: Programming Language :: Python :: 3.7
Classifier: Programming Language :: Python :: 3.8
Classifier: Programming Language :: Python :: 3.9
License-File: LICENSE
